pwdgen.py
pwd_generator-2.0.0.dist-info/METADATA
pwd_generator-2.0.0.dist-info/WHEEL
pwd_generator-2.0.0.dist-info/entry_points.txt
pwd_generator-2.0.0.dist-info/RECORD
