Metadata-Version: 2.1
Name: pwd-generator
Version: 2.0.0
Summary: A simple password generator
License: MIT
Author: RadoTheProgrammer
Author-email: rado@arazakar.com
Requires-Python: >=3.11,<4.0
Classifier: License :: OSI Approved :: MIT License
Classifier: Programming Language :: Python :: 3
Classifier: Programming Language :: Python :: 3.11
Classifier: Programming Language :: Python :: 3.12
